loguru_caplog/__init__.py
loguru_caplog/loguru_caplog.py
loguru_caplog-0.2.0.dist-info/LICENSE
loguru_caplog-0.2.0.dist-info/METADATA
loguru_caplog-0.2.0.dist-info/WHEEL
loguru_caplog-0.2.0.dist-info/top_level.txt
loguru_caplog-0.2.0.dist-info/RECORD
