Metadata-Version: 2.1
Name: loguru-caplog
Version: 0.2.0
Summary: Сaptures loguru logging output
Home-page: UNKNOWN
Author: Dinn757
License: MIT
Platform: UNKNOWN
Classifier: Programming Language :: Python :: 3
Classifier: License :: OSI Approved :: MIT License
Classifier: Operating System :: OS Independent
Classifier: Development Status :: 4 - Beta
Requires-Python: >=3.6
Requires-Dist: loguru
Requires-Dist: pytest
